setup.py
sancomp/calculations.py
sancomp/face-elasticidade-poisson.dat
sancomp/nucleo-elasticidade.dat
sancomp/sancomp.py
sancomp/sancomp.spec
sancomp/sancompt.ui
sancomp.egg-info/PKG-INFO
sancomp.egg-info/SOURCES.txt
sancomp.egg-info/dependency_links.txt
sancomp.egg-info/requires.txt
sancomp.egg-info/top_level.txt
sancomp/image/beam.png
sancomp/image/sancomp.ico
sancomp/image/sancomp.iss
sancomp/image/sancomp.png
sancomp/image/sancomp_logo.png
sancomp/image/sancomp_logo1.bmp
sancomp/image/sancomp_logo1.png
sancomp/image/sec2.png
sancomp/image/v0.png
sancomp/image/v1.png
sancomp/image/v2.png
sancomp/image/v3.png
sancomp/image/v4.png
sancomp/image/v5.png
sancomp/image/v6.png
sancomp/image/v7.png