Metadata-Version: 1.0
Name: sancomp
Version: 1.2b12
Summary: Sandwich Structures Analysis Software
Home-page: https://github.com/douglaskorvo/sancomp
Author: Douglas Rodrigues
Author-email: douglas.souza85@gmail.com
License: GPL 3.0
Keywords: sandwich structures analysis software
Platform: UNKNOWN
